mathjson_solver/__init__.py
mathjson_solver/__main__.py
mathjson_solver-1.18.0.dist-info/licenses/LICENSE
mathjson_solver-1.18.0.dist-info/METADATA
mathjson_solver-1.18.0.dist-info/WHEEL
mathjson_solver-1.18.0.dist-info/top_level.txt
mathjson_solver-1.18.0.dist-info/RECORD
