Metadata-Version: 2.4
Name: mathjson-solver
Version: 1.18.0
Summary: Utilities for MathJSON evaluation
Home-page: https://github.com/LongenesisLtd/mathjson-solver
Author: Martins Mednis
Author-email: mrt@mednis.info
Project-URL: Bug Tracker, https://github.com/LongenesisLtd/mathjson-solver/issues
Classifier: Programming Language :: Python :: 3
Classifier: Operating System :: OS Independent
Requires-Python: >=3.6
License-File: LICENSE
Dynamic: author
Dynamic: author-email
Dynamic: classifier
Dynamic: description
Dynamic: description-content-type
Dynamic: home-page
Dynamic: license-file
Dynamic: project-url
Dynamic: requires-python
Dynamic: summary
